triceratops/__init__.py
triceratops/funcs.py
triceratops/likelihoods.py
triceratops/marginal_likelihoods.py
triceratops/priors.py
triceratops/triceratops.py
triceratops/data/ldc_kepler.csv
triceratops/data/ldc_tess.csv
triceratops/data/temp.txt
triceratops-1.0.19.dist-info/LICENSE
triceratops-1.0.19.dist-info/METADATA
triceratops-1.0.19.dist-info/WHEEL
triceratops-1.0.19.dist-info/top_level.txt
triceratops-1.0.19.dist-info/RECORD
