Metadata-Version: 2.1
Name: triceratops
Version: 1.0.19
Summary: Statistical Validation of Transiting Planet Candidates
Home-page: https://github.com/stevengiacalone/triceratops
Author: Steven Giacalone
Author-email: steven_giacalone@berkeley.edu
License: UNKNOWN
Platform: UNKNOWN
Classifier: Development Status :: 5 - Production/Stable
Classifier: Intended Audience :: Science/Research
Classifier: Operating System :: OS Independent
Classifier: Programming Language :: Python :: 3
Classifier: License :: OSI Approved :: MIT License
Classifier: Topic :: Scientific/Engineering :: Astronomy
Requires-Dist: numpy >=1.18.1
Requires-Dist: pandas >=0.23.4
Requires-Dist: scipy >=1.1.0
Requires-Dist: matplotlib >=3.5.1
Requires-Dist: astropy >=4.0
Requires-Dist: astroquery >=0.4.6
Requires-Dist: pytransit >=2.2
Requires-Dist: mechanicalsoup >=0.12.0
Requires-Dist: emcee >=3.0.2
Requires-Dist: seaborn >=0.11.1
Requires-Dist: numba >=0.52.0
Requires-Dist: pyrr >=0.10.3
Requires-Dist: celerite >=0.4.0
Requires-Dist: lightkurve >=2.0.0
Requires-Dist: arviz >=0.12.1
Requires-Dist: corner >=2.2.1
Requires-Dist: beautifulsoup4 >=4.11.1
